{
  "projects": {
    "development": {
      "project_id": "event-ticket-website-6b541",
      "project_number": "423743096823",
      "display_name": "Event Ticket Website Development",
      "name": "projects/event-ticket-website-6b541",
      "state": "ACTIVE"
    },
    "staging": {
      "project_id": "ravehub-staging",
      "project_number": "123456789013",
      "display_name": "Ravehub Staging",
      "name": "projects/ravehub-staging",
      "state": "ACTIVE"
    },
    "production": {
      "project_id": "event-ticket-website-6b541",
      "project_number": "123456789014",
      "display_name": "Ravehub Production",
      "name": "projects/event-ticket-website-6b541",
      "state": "ACTIVE"
    }
  },
  "client": {
    "api_key": {
      "current_key": "AIzaSyBzSPow2dSdqKOX79Vi7VvsZXg_M8lc730"
    }
  },
  "configuration_version": "1"
}